chart_pkg/__init__.py
chart_pkg/pie_chart.py
Plotly_styled_charts_pkg-0.0.0.dist-info/LICENSE
Plotly_styled_charts_pkg-0.0.0.dist-info/METADATA
Plotly_styled_charts_pkg-0.0.0.dist-info/WHEEL
Plotly_styled_charts_pkg-0.0.0.dist-info/top_level.txt
Plotly_styled_charts_pkg-0.0.0.dist-info/RECORD
