Metadata-Version: 2.1
Name: Plotly_styled_charts_pkg
Version: 0.0.0
Summary: Styled charts from plotly.
Author: Chetan Arvind Londhe
Author-email: chetanlondhe1112@gmail.com
License: MIT
Keywords: python,plotly,pandas,style,charts
Classifier: Development Status :: 1 - Planning
Classifier: Intended Audience :: Developers
Classifier: Programming Language :: Python :: 3
Classifier: Operating System :: Unix
Classifier: Operating System :: MacOS :: MacOS X
Classifier: Operating System :: Microsoft :: Windows
License-File: LICENSE
